py3a2-0.1.5.dist-info/METADATA
py3a2-0.1.5.dist-info/WHEEL
py3a2/__init__.py
py3a2/py3a2.cpython-38-x86_64-linux-gnu.so
py3a2-0.1.5.dist-info/RECORD
