Metadata-Version: 2.1
Name: py3a2
Version: 0.1.5
